openmatrix/Exceptions.py
openmatrix/File.py
openmatrix/__init__.py
openmatrix/validator.py
OpenMatrix-0.3.5.0.dist-info/LICENSE.TXT
OpenMatrix-0.3.5.0.dist-info/METADATA
OpenMatrix-0.3.5.0.dist-info/WHEEL
OpenMatrix-0.3.5.0.dist-info/entry_points.txt
OpenMatrix-0.3.5.0.dist-info/top_level.txt
OpenMatrix-0.3.5.0.dist-info/RECORD
