Metadata-Version: 1.1
Name: OpenMatrix
Version: 0.3.5.0
Summary: OMX, the open matrix data format
Home-page: https://github.com/osPlanning/omx
Author: Billy Charlton, Ben Stabler
Author-email: billy@okbecause.com, benstabler@yahoo.com
License: Apache
Keywords: openmatrix omx
Platform: UNKNOWN
Classifier: License :: OSI Approved :: Apache Software License
